mdformat_mkdocs/__init__.py
mdformat_mkdocs/_helpers.py
mdformat_mkdocs/_normalize_list.py
mdformat_mkdocs/_postprocess_inline.py
mdformat_mkdocs/_synced/__init__.py
mdformat_mkdocs/_synced/admon_factories/README.md
mdformat_mkdocs/_synced/admon_factories/__init__.py
mdformat_mkdocs/_synced/admon_factories/_whitespace_admon_factories.py
mdformat_mkdocs/mdit_plugins/__init__.py
mdformat_mkdocs/mdit_plugins/_material_admon.py
mdformat_mkdocs/mdit_plugins/_material_content_tabs.py
mdformat_mkdocs/mdit_plugins/_material_deflist.py
mdformat_mkdocs/mdit_plugins/_mkdocstrings_autorefs.py
mdformat_mkdocs/mdit_plugins/_mkdocstrings_crossreference.py
mdformat_mkdocs/mdit_plugins/_pymd_abbreviations.py
mdformat_mkdocs/mdit_plugins/_pymd_admon.py
mdformat_mkdocs/mdit_plugins/_pymd_arithmatex.py
mdformat_mkdocs/mdit_plugins/_pymd_captions.py
mdformat_mkdocs/mdit_plugins/_pymd_snippet.py
mdformat_mkdocs/mdit_plugins/_python_markdown_attr_list.py
mdformat_mkdocs/plugin.py
mdformat_mkdocs/py.typed
mdformat_mkdocs-5.1.4.dist-info/licenses/LICENSE
mdformat_mkdocs-5.1.4.dist-info/WHEEL
mdformat_mkdocs-5.1.4.dist-info/entry_points.txt
mdformat_mkdocs-5.1.4.dist-info/METADATA
mdformat_mkdocs-5.1.4.dist-info/RECORD
