Metadata-Version: 2.4
Name: mdformat_mkdocs
Version: 5.1.4
Summary: An mdformat plugin for mkdocs and Material for MkDocs
Keywords: markdown,markdown-it,mdformat,mdformat_plugin_template
Author: kyleking
Author-email: kyleking <dev.act.kyle@gmail.com>
License-Expression: MIT
License-File: LICENSE
Classifier: Intended Audience :: Developers
Classifier: License :: OSI Approved :: MIT License
Classifier: Programming Language :: Python :: 3
Classifier: Topic :: Software Development :: Libraries :: Python Modules
Requires-Dist: mdformat>=0.7.19
Requires-Dist: mdformat-gfm>=0.3.6
Requires-Dist: mdit-py-plugins>=0.4.1
Requires-Dist: more-itertools>=10.5.0
Requires-Dist: mdformat-beautysh>=0.1.1 ; extra == 'recommended'
Requires-Dist: mdformat-config>=0.2.1 ; extra == 'recommended'
Requires-Dist: mdformat-footnote>=0.1.1 ; extra == 'recommended'
Requires-Dist: mdformat-front-matters>=0.1.0 ; extra == 'recommended'
Requires-Dist: mdformat-gfm>=1.0.0 ; extra == 'recommended'
Requires-Dist: mdformat-ruff>=0.1.3 ; extra == 'recommended'
Requires-Dist: mdformat-simple-breaks>=0.0.1 ; extra == 'recommended'
Requires-Dist: mdformat-web>=0.2.0 ; extra == 'recommended'
Requires-Dist: mdformat-wikilink>=0.2.0 ; extra == 'recommended'
Requires-Dist: setuptools ; extra == 'recommended'
Requires-Dist: mdformat-footnote>=0.1.0 ; extra == 'recommended-mdsf'
Requires-Dist: mdformat-front-matters>=1.0.1 ; extra == 'recommended-mdsf'
Requires-Dist: mdformat-gfm>=1.0.0 ; extra == 'recommended-mdsf'
Requires-Dist: mdformat-hooks>=0.1.0 ; extra == 'recommended-mdsf'
Requires-Dist: mdformat-simple-breaks>=0.0.1 ; extra == 'recommended-mdsf'
Requires-Dist: mdformat-wikilink>=0.2.0 ; extra == 'recommended-mdsf'
Requires-Dist: beartype>=0.21.0 ; extra == 'test'
Requires-Dist: pytest>=9.0.1 ; extra == 'test'
Requires-Dist: pytest-beartype>=0.2.0 ; extra == 'test'
Requires-Dist: pytest-cov>=7.0.0 ; extra == 'test'
Requires-Dist: syrupy>=4.9.1 ; extra == 'test'
Requires-Python: >=3.10.0
Project-URL: Bug Tracker, https://github.com/kyleking/mdformat-mkdocs/issues
Project-URL: Changelog, https://github.com/kyleking/mdformat-mkdocs/releases
Project-URL: homepage, https://github.com/kyleking/mdformat-mkdocs
Provides-Extra: recommended
Provides-Extra: recommended-mdsf
Provides-Extra: test
